pycyclone.cpython-39-x86_64-linux-gnu.so
router
pycyclone-0.4.3.dist-info/top_level.txt
pycyclone-0.4.3.dist-info/WHEEL
pycyclone-0.4.3.dist-info/METADATA
pycyclone-0.4.3.dist-info/RECORD
pycyclone-0.4.3.data/scripts/router
