Metadata-Version: 2.1
Name: pycyclone
Version: 0.4.3
Summary: Fast CGRA Routing
Home-page: https://github.com/Kuree/cgra_pnr/tree/master/cyclone
Author: Keyi Zhang
Author-email: keyi@stanford.edu
